pyfit/__init__.py
pyfit/data.py
pyfit/engine.py
pyfit/metrics.py
pyfit/nn.py
pyfit/optim.py
pyfit/train.py
pyfit-1.0.2.dist-info/LICENSE
pyfit-1.0.2.dist-info/METADATA
pyfit-1.0.2.dist-info/WHEEL
pyfit-1.0.2.dist-info/RECORD
