Metadata-Version: 2.1
Name: pyfit
Version: 1.0.2
Summary: A minimalist neural networks library built on a tiny autograd engine
Home-page: https://github.com/bpesquet/pyfit
License: MIT
Author: Baptiste Pesquet
Author-email: bpesquet@gmail.com
Requires-Python: >=3.9,<4.0
Classifier: License :: OSI Approved :: MIT License
Classifier: Programming Language :: Python :: 3
Classifier: Programming Language :: Python :: 3.9
Classifier: Programming Language :: Python :: 3.10
Classifier: Programming Language :: Python :: 3.11
Classifier: Programming Language :: Python :: 3.12
Project-URL: Repository, https://github.com/bpesquet/pyfit
